{
  "data": [
    {
      "website": "http://hfw.org.uk/", 
      "email\r": "info@h4w.co.uk", 
      "tel": "020 7501 6120", 
      "area": "234-244 Stockwell Road", 
      "process": "", 
      "organisation": "Housing for Women ", 
      "clients": "Victims of domestic violence, trafficking ", 
      "services": "Empowering women through providing good quality homes, and support to women who have experienced domestic violence, trafficking and mothers leaving prison.", 
      "borough": "Lambeth ", 
      "type": "Trafficking", 
      "day": ""
    }, 
    {
      "website": "http://hfw.org.uk/", 
      "area": "234-244 Stockwell Road", 
      "process": "", 
      "organisation": "Housing for Women ", 
      "clients": "Victims of domestic violence, trafficking ", 
      "telephone": "020 7501 6120", 
      "day": "", 
      "address\r": "", 
      "services": "Empowering women through providing good quality homes, and support to women who have experienced domestic violence, trafficking and mothers leaving prison.", 
      "borough": "Lambeth ", 
      "type": "Women-DV", 
      "email": "info@h4w.co.uk"
    }
  ]
}